django33_ninja/__init__.py
django33_ninja/compatibility/__init__.py
django33_ninja/compatibility/util.py
django33_ninja/conf.py
django33_ninja/constants.py
django33_ninja/decorators.py
django33_ninja/errors.py
django33_ninja/files.py
django33_ninja/filter_schema.py
django33_ninja/main.py
django33_ninja/management/__init__.py
django33_ninja/management/commands/__init__.py
django33_ninja/management/commands/export_openapi_schema.py
django33_ninja/management/utils.py
django33_ninja/openapi/__init__.py
django33_ninja/openapi/docs.py
django33_ninja/openapi/schema.py
django33_ninja/openapi/urls.py
django33_ninja/openapi/views.py
django33_ninja/operation.py
django33_ninja/orm/__init__.py
django33_ninja/orm/factory.py
django33_ninja/orm/fields.py
django33_ninja/orm/metaclass.py
django33_ninja/orm/shortcuts.py
django33_ninja/pagination.py
django33_ninja/params/__init__.py
django33_ninja/params/functions.py
django33_ninja/params/models.py
django33_ninja/parser.py
django33_ninja/patch_dict.py
django33_ninja/py.typed
django33_ninja/renderers.py
django33_ninja/responses.py
django33_ninja/router.py
django33_ninja/schema.py
django33_ninja/security/__init__.py
django33_ninja/security/apikey.py
django33_ninja/security/base.py
django33_ninja/security/http.py
django33_ninja/security/session.py
django33_ninja/signature/__init__.py
django33_ninja/signature/details.py
django33_ninja/signature/utils.py
django33_ninja/static/ninja/favicon.png
django33_ninja/static/ninja/redoc.standalone.js
django33_ninja/static/ninja/redoc.standalone.js.map
django33_ninja/static/ninja/swagger-ui-bundle.js
django33_ninja/static/ninja/swagger-ui-bundle.js.map
django33_ninja/static/ninja/swagger-ui-init.js
django33_ninja/static/ninja/swagger-ui.css
django33_ninja/static/ninja/swagger-ui.css.map
django33_ninja/templates/django33_ninja/redoc.html
django33_ninja/templates/django33_ninja/redoc_cdn.html
django33_ninja/templates/django33_ninja/swagger.html
django33_ninja/templates/django33_ninja/swagger_cdn.html
django33_ninja-0.1.2.dist-info/LICENSE
django33_ninja-0.1.2.dist-info/METADATA
django33_ninja-0.1.2.dist-info/WHEEL
django33_ninja-0.1.2.dist-info/RECORD
