Metadata-Version: 2.1
Name: django33-ninja
Version: 0.1.2
Summary: django33-ninja 是一个使用Django和Python 3.6+ 类型提示构建api的web框架。
Author: zhangdapeng
Author-email: 1156956636@qq.com
Requires-Python: >=3.12,<4.0
Classifier: Programming Language :: Python :: 3
Classifier: Programming Language :: Python :: 3.12
Classifier: Programming Language :: Python :: 3.13
Requires-Dist: pydantic (>=2.10.5,<3.0.0)
